LICENCE.txt
MANIFEST.in
README.rst
setup.cfg
setup.py
emencia_request_form.egg-info/PKG-INFO
emencia_request_form.egg-info/SOURCES.txt
emencia_request_form.egg-info/dependency_links.txt
emencia_request_form.egg-info/requires.txt
emencia_request_form.egg-info/top_level.txt
emencia_request_form.egg-info/zip-safe
request_form/__init__.py
request_form/apps.py
request_form/cms_plugins.py
request_form/exceptions.py
request_form/settings.py
request_form/urls.py
request_form/admin/__init__.py
request_form/admin/admin.py
request_form/factories/__init__.py
request_form/factories/cms.py
request_form/factories/request.py
request_form/factories/user.py
request_form/form_helpers/__init__.py
request_form/forms/__init__.py
request_form/forms/forms.py
request_form/migrations/0001_initial.py
request_form/migrations/__init__.py
request_form/models/__init__.py
request_form/models/request.py
request_form/plugins/__init__.py
request_form/plugins/request.py
request_form/templates/request_form/base.html
request_form/templates/request_form/request/email.txt
request_form/templates/request_form/request/form.html
request_form/templates/request_form/request/form_success.html
request_form/templates/request_form/request/plugin.html
request_form/utils/__init__.py
request_form/utils/cms_tests.py
request_form/utils/network.py
request_form/utils/parsers.py
request_form/utils/tests.py
request_form/views/__init__.py
request_form/views/views.py