Metadata-Version: 2.1
Name: emencia-request-form
Version: 0.1.0
Summary: A simple contact form with some homemade antispam.
Home-page: https://github.com/emencia/emencia-request-form
Author: Emencia
Author-email: support@emencia.com
License: MIT
Project-URL: Source Code, https://github.com/emencia/emencia-request-form
Project-URL: Issue Tracker, https://github.com/emencia/emencia-request-form/issues
Project-URL: Changelog, https://emencia-request-form.readthedocs.io/en/latest/history.html
Project-URL: Documentation, https://emencia-request-form.readthedocs.io/
Keywords: Python,Django,django-cms
Classifier: Development Status :: 2 - Pre-Alpha
Classifier: Intended Audience :: Developers
Classifier: License :: OSI Approved :: MIT License
Classifier: Natural Language :: English
Classifier: Programming Language :: Python :: 3
Classifier: Programming Language :: Python :: 3.10
Classifier: Programming Language :: Python :: 3.11
Classifier: Framework :: Django
Classifier: Framework :: Django :: 4.0
Classifier: Framework :: Django :: 4.1
Classifier: Framework :: Django :: 4.2
License-File: LICENCE.txt
Requires-Dist: Django<5.0,>=4.0
Requires-Dist: django-cms<4.0,>=3.11.0
Requires-Dist: djangocms-text-ckeditor>=5.0.1
Requires-Dist: django-phonenumber-field[phonenumbers]<8.0,>=7.2.0
Requires-Dist: django-simple-captcha<1.0,>=0.5.20
Requires-Dist: django-crispy-forms>=2.0
Requires-Dist: crispy-bootstrap5>=0.7
Provides-Extra: dev
Requires-Dist: pytest; extra == "dev"
Requires-Dist: pytest-django; extra == "dev"
Requires-Dist: factory-boy; extra == "dev"
Requires-Dist: pyquery; extra == "dev"
Requires-Dist: freezegun; extra == "dev"
Provides-Extra: quality
Requires-Dist: flake8; extra == "quality"
Requires-Dist: tox; extra == "quality"
Provides-Extra: doc
Requires-Dist: sphinx; extra == "doc"
Requires-Dist: furo==2023.7.26; extra == "doc"
Requires-Dist: sphinx-copybutton==0.5.2; extra == "doc"
Provides-Extra: doc-live
Requires-Dist: livereload; extra == "doc-live"
Provides-Extra: release
Requires-Dist: twine; extra == "release"
